{
  "indexes": [
    {
      "collectionGroup": "news",
      "queryScope": "COLLECTION",
      "fields": [
        {
          "fieldPath": "category",
          "order": "ASCENDING"
        },
        {
          "fieldPath": "timestamp",
          "order": "DESCENDING"
        }
      ]
    },
    {
      "collectionGroup": "news",
      "queryScope": "COLLECTION",
      "fields": [
        {
          "fieldPath": "language",
          "order": "ASCENDING"
        },
        {
          "fieldPath": "timestamp",
          "order": "DESCENDING"
        }
      ]
    },
    {
      "collectionGroup": "news",
      "queryScope": "COLLECTION",
      "fields": [
        {
          "fieldPath": "location.state",
          "order": "ASCENDING"
        },
        {
          "fieldPath": "timestamp",
          "order": "DESCENDING"
        }
      ]
    },
    {
      "collectionGroup": "buzz",
      "queryScope": "COLLECTION",
      "fields": [
        {
          "fieldPath": "viral",
          "order": "DESCENDING"
        },
        {
          "fieldPath": "timestamp",
          "order": "DESCENDING"
        }
      ]
    }
  ],
  "fieldOverrides": []
}
